setup.cfg
setup.py
test/test.py
twe_parser/__init__.py
twe_parser/twe_responce.py
twe_parser.egg-info/PKG-INFO
twe_parser.egg-info/SOURCES.txt
twe_parser.egg-info/dependency_links.txt
twe_parser.egg-info/pbr.json
twe_parser.egg-info/top_level.txt