Metadata-Version: 1.1
Name: twe-parser
Version: 0.0.4
Summary: TWE-Lite's serial responce Parser
Home-page: https://github.com/nc30/twe_parser
Author: Asahi Himura
Author-email: himura@nitolab.com
License: MIT
Download-URL: https://github.com/nc30/twe_parser/tarball/0.0.4
Keywords: TWE-Lite
Platform: UNKNOWN
